funcaitools.py
funcaitools-0.0.1.dist-info/LICENSE
funcaitools-0.0.1.dist-info/METADATA
funcaitools-0.0.1.dist-info/WHEEL
funcaitools-0.0.1.dist-info/top_level.txt
funcaitools-0.0.1.dist-info/RECORD
