Metadata-Version: 2.1
Name: funcaitools
Version: 0.0.1
Summary: artificial intelligence
Author: unknown
Author-email: noone@gmail.com
License: MIT
Keywords: artificial intelligence
Classifier: Programming Language :: Python :: 3
Classifier: License :: OSI Approved :: MIT License
Classifier: Operating System :: OS Independent
Requires-Python: >=3.7
License-File: LICENSE
Requires-Dist: pyailab
